{".class": "MypyFile", "_fullname": "quiz.serializers", "is_partial_stub_package": false, "is_stub": false, "names": {".class": "SymbolTable", "Answer": {".class": "SymbolTableNode", "cross_ref": "quiz.models.Answer", "kind": "Gdef"}, "AnswerSerializer": {".class": "SymbolTableNode", "kind": "Gdef", "node": {".class": "TypeInfo", "_promote": null, "abstract_attributes": [], "bases": ["builtins.object"], "declared_metaclass": null, "defn": {".class": "ClassDef", "fullname": "quiz.serializers.AnswerSerializer", "name": "AnswerSerializer", "type_vars": []}, "flags": ["fallback_to_any"], "fullname": "quiz.serializers.AnswerSerializer", "metaclass_type": null, "metadata": {}, "module_name": "quiz.serializers", "mro": ["quiz.serializers.AnswerSerializer", "builtins.object"], "names": {".class": "SymbolTable", "Meta": {".class": "SymbolTableNode", "kind": "Mdef", "node": {".class": "TypeInfo", "_promote": null, "abstract_attributes": [], "bases": ["builtins.object"], "declared_metaclass": null, "defn": {".class": "ClassDef", "fullname": "quiz.serializers.AnswerSerializer.Meta", "name": "Meta", "type_vars": []}, "flags": [], "fullname": "quiz.serializers.AnswerSerializer.Meta", "metaclass_type": null, "metadata": {}, "module_name": "quiz.serializers", "mro": ["quiz.serializers.AnswerSerializer.Meta", "builtins.object"], "names": {".class": "SymbolTable", "fields": {".class": "SymbolTableNode", "kind": "Mdef", "node": {".class": "Var", "flags": ["is_initialized_in_class"], "fullname": "quiz.serializers.AnswerSerializer.Meta.fields", "name": "fields", "type": {".class": "Instance", "args": ["builtins.str"], "type_ref": "builtins.list"}}}, "model": {".class": "SymbolTableNode", "kind": "Mdef", "node": {".class": "Var", "flags": ["is_initialized_in_class"], "fullname": "quiz.serializers.AnswerSerializer.Meta.model", "name": "model", "type": {".class": "CallableType", "arg_kinds": [2, 4], "arg_names": ["_args", "_kwds"], "arg_types": [{".class": "AnyType", "missing_import_name": null, "source_any": null, "type_of_any": 6}, {".class": "AnyType", "missing_import_name": null, "source_any": null, "type_of_any": 6}], "bound_args": [], "def_extras": {}, "fallback": "builtins.type", "implicit": false, "is_ellipsis_args": false, "name": null, "ret_type": "quiz.models.Answer", "variables": []}}}}, "tuple_type": null, "type_vars": [], "typeddict_type": null}}}, "tuple_type": null, "type_vars": [], "typeddict_type": null}}, "Question": {".class": "SymbolTableNode", "cross_ref": "quiz.models.Question", "kind": "Gdef"}, "QuestionSerializer": {".class": "SymbolTableNode", "kind": "Gdef", "node": {".class": "TypeInfo", "_promote": null, "abstract_attributes": [], "bases": ["builtins.object"], "declared_metaclass": null, "defn": {".class": "ClassDef", "fullname": "quiz.serializers.QuestionSerializer", "name": "QuestionSerializer", "type_vars": []}, "flags": ["fallback_to_any"], "fullname": "quiz.serializers.QuestionSerializer", "metaclass_type": null, "metadata": {}, "module_name": "quiz.serializers", "mro": ["quiz.serializers.QuestionSerializer", "builtins.object"], "names": {".class": "SymbolTable", "Meta": {".class": "SymbolTableNode", "kind": "Mdef", "node": {".class": "TypeInfo", "_promote": null, "abstract_attributes": [], "bases": ["builtins.object"], "declared_metaclass": null, "defn": {".class": "ClassDef", "fullname": "quiz.serializers.QuestionSerializer.Meta", "name": "Meta", "type_vars": []}, "flags": [], "fullname": "quiz.serializers.QuestionSerializer.Meta", "metaclass_type": null, "metadata": {}, "module_name": "quiz.serializers", "mro": ["quiz.serializers.QuestionSerializer.Meta", "builtins.object"], "names": {".class": "SymbolTable", "fields": {".class": "SymbolTableNode", "kind": "Mdef", "node": {".class": "Var", "flags": ["is_initialized_in_class"], "fullname": "quiz.serializers.QuestionSerializer.Meta.fields", "name": "fields", "type": {".class": "Instance", "args": ["builtins.str"], "type_ref": "builtins.list"}}}, "model": {".class": "SymbolTableNode", "kind": "Mdef", "node": {".class": "Var", "flags": ["is_initialized_in_class"], "fullname": "quiz.serializers.QuestionSerializer.Meta.model", "name": "model", "type": {".class": "CallableType", "arg_kinds": [2, 4], "arg_names": ["_args", "_kwds"], "arg_types": [{".class": "AnyType", "missing_import_name": null, "source_any": null, "type_of_any": 6}, {".class": "AnyType", "missing_import_name": null, "source_any": null, "type_of_any": 6}], "bound_args": [], "def_extras": {}, "fallback": "builtins.type", "implicit": false, "is_ellipsis_args": false, "name": null, "ret_type": "quiz.models.Question", "variables": []}}}}, "tuple_type": null, "type_vars": [], "typeddict_type": null}}, "answers": {".class": "SymbolTableNode", "kind": "Mdef", "node": {".class": "Var", "flags": ["is_initialized_in_class"], "fullname": "quiz.serializers.QuestionSerializer.answers", "name": "answers", "type": "quiz.serializers.AnswerSerializer"}}, "create": {".class": "SymbolTableNode", "kind": "Mdef", "node": {".class": "FuncDef", "arg_kinds": [0, 0], "arg_names": ["self", "validated_data"], "flags": [], "fullname": "quiz.serializers.QuestionSerializer.create", "name": "create", "type": null}}, "skill_type": {".class": "SymbolTableNode", "kind": "Mdef", "node": {".class": "Var", "flags": ["is_initialized_in_class"], "fullname": "quiz.serializers.QuestionSerializer.skill_type", "name": "skill_type", "type": "quiz.serializers.SkillTypeSerializer"}}}, "tuple_type": null, "type_vars": [], "typeddict_type": null}}, "Quiz": {".class": "SymbolTableNode", "cross_ref": "quiz.models.Quiz", "kind": "Gdef"}, "QuizInstance": {".class": "SymbolTableNode", "cross_ref": "quiz.models.QuizInstance", "kind": "Gdef"}, "QuizInstanceSerializer": {".class": "SymbolTableNode", "kind": "Gdef", "node": {".class": "TypeInfo", "_promote": null, "abstract_attributes": [], "bases": ["builtins.object"], "declared_metaclass": null, "defn": {".class": "ClassDef", "fullname": "quiz.serializers.QuizInstanceSerializer", "name": "QuizInstanceSerializer", "type_vars": []}, "flags": ["fallback_to_any"], "fullname": "quiz.serializers.QuizInstanceSerializer", "metaclass_type": null, "metadata": {}, "module_name": "quiz.serializers", "mro": ["quiz.serializers.QuizInstanceSerializer", "builtins.object"], "names": {".class": "SymbolTable", "Meta": {".class": "SymbolTableNode", "kind": "Mdef", "node": {".class": "TypeInfo", "_promote": null, "abstract_attributes": [], "bases": ["builtins.object"], "declared_metaclass": null, "defn": {".class": "ClassDef", "fullname": "quiz.serializers.QuizInstanceSerializer.Meta", "name": "Meta", "type_vars": []}, "flags": [], "fullname": "quiz.serializers.QuizInstanceSerializer.Meta", "metaclass_type": null, "metadata": {}, "module_name": "quiz.serializers", "mro": ["quiz.serializers.QuizInstanceSerializer.Meta", "builtins.object"], "names": {".class": "SymbolTable", "fields": {".class": "SymbolTableNode", "kind": "Mdef", "node": {".class": "Var", "flags": ["is_initialized_in_class"], "fullname": "quiz.serializers.QuizInstanceSerializer.Meta.fields", "name": "fields", "type": {".class": "Instance", "args": ["builtins.str"], "type_ref": "builtins.list"}}}, "model": {".class": "SymbolTableNode", "kind": "Mdef", "node": {".class": "Var", "flags": ["is_initialized_in_class"], "fullname": "quiz.serializers.QuizInstanceSerializer.Meta.model", "name": "model", "type": {".class": "CallableType", "arg_kinds": [2, 4], "arg_names": ["_args", "_kwds"], "arg_types": [{".class": "AnyType", "missing_import_name": null, "source_any": null, "type_of_any": 6}, {".class": "AnyType", "missing_import_name": null, "source_any": null, "type_of_any": 6}], "bound_args": [], "def_extras": {}, "fallback": "builtins.type", "implicit": false, "is_ellipsis_args": false, "name": null, "ret_type": "quiz.models.QuizInstance", "variables": []}}}}, "tuple_type": null, "type_vars": [], "typeddict_type": null}}, "questions": {".class": "SymbolTableNode", "kind": "Mdef", "node": {".class": "Var", "flags": ["is_initialized_in_class"], "fullname": "quiz.serializers.QuizInstanceSerializer.questions", "name": "questions", "type": "quiz.serializers.QuestionSerializer"}}}, "tuple_type": null, "type_vars": [], "typeddict_type": null}}, "QuizSerializer": {".class": "SymbolTableNode", "kind": "Gdef", "node": {".class": "TypeInfo", "_promote": null, "abstract_attributes": [], "bases": ["builtins.object"], "declared_metaclass": null, "defn": {".class": "ClassDef", "fullname": "quiz.serializers.QuizSerializer", "name": "QuizSerializer", "type_vars": []}, "flags": ["fallback_to_any"], "fullname": "quiz.serializers.QuizSerializer", "metaclass_type": null, "metadata": {}, "module_name": "quiz.serializers", "mro": ["quiz.serializers.QuizSerializer", "builtins.object"], "names": {".class": "SymbolTable", "Meta": {".class": "SymbolTableNode", "kind": "Mdef", "node": {".class": "TypeInfo", "_promote": null, "abstract_attributes": [], "bases": ["builtins.object"], "declared_metaclass": null, "defn": {".class": "ClassDef", "fullname": "quiz.serializers.QuizSerializer.Meta", "name": "Meta", "type_vars": []}, "flags": [], "fullname": "quiz.serializers.QuizSerializer.Meta", "metaclass_type": null, "metadata": {}, "module_name": "quiz.serializers", "mro": ["quiz.serializers.QuizSerializer.Meta", "builtins.object"], "names": {".class": "SymbolTable", "fields": {".class": "SymbolTableNode", "kind": "Mdef", "node": {".class": "Var", "flags": ["is_initialized_in_class"], "fullname": "quiz.serializers.QuizSerializer.Meta.fields", "name": "fields", "type": {".class": "Instance", "args": ["builtins.str"], "type_ref": "builtins.list"}}}, "model": {".class": "SymbolTableNode", "kind": "Mdef", "node": {".class": "Var", "flags": ["is_initialized_in_class"], "fullname": "quiz.serializers.QuizSerializer.Meta.model", "name": "model", "type": {".class": "CallableType", "arg_kinds": [2, 4], "arg_names": ["_args", "_kwds"], "arg_types": [{".class": "AnyType", "missing_import_name": null, "source_any": null, "type_of_any": 6}, {".class": "AnyType", "missing_import_name": null, "source_any": null, "type_of_any": 6}], "bound_args": [], "def_extras": {}, "fallback": "builtins.type", "implicit": false, "is_ellipsis_args": false, "name": null, "ret_type": "quiz.models.Quiz", "variables": []}}}}, "tuple_type": null, "type_vars": [], "typeddict_type": null}}, "create": {".class": "SymbolTableNode", "kind": "Mdef", "node": {".class": "FuncDef", "arg_kinds": [0, 0], "arg_names": ["self", "validated_data"], "flags": [], "fullname": "quiz.serializers.QuizSerializer.create", "name": "create", "type": null}}, "skill_type": {".class": "SymbolTableNode", "kind": "Mdef", "node": {".class": "Var", "flags": ["is_initialized_in_class"], "fullname": "quiz.serializers.QuizSerializer.skill_type", "name": "skill_type", "type": "quiz.serializers.SkillTypeSerializer"}}}, "tuple_type": null, "type_vars": [], "typeddict_type": null}}, "SkillType": {".class": "SymbolTableNode", "cross_ref": "quiz.models.SkillType", "kind": "Gdef"}, "SkillTypeSerializer": {".class": "SymbolTableNode", "kind": "Gdef", "node": {".class": "TypeInfo", "_promote": null, "abstract_attributes": [], "bases": ["builtins.object"], "declared_metaclass": null, "defn": {".class": "ClassDef", "fullname": "quiz.serializers.SkillTypeSerializer", "name": "SkillTypeSerializer", "type_vars": []}, "flags": ["fallback_to_any"], "fullname": "quiz.serializers.SkillTypeSerializer", "metaclass_type": null, "metadata": {}, "module_name": "quiz.serializers", "mro": ["quiz.serializers.SkillTypeSerializer", "builtins.object"], "names": {".class": "SymbolTable", "Meta": {".class": "SymbolTableNode", "kind": "Mdef", "node": {".class": "TypeInfo", "_promote": null, "abstract_attributes": [], "bases": ["builtins.object"], "declared_metaclass": null, "defn": {".class": "ClassDef", "fullname": "quiz.serializers.SkillTypeSerializer.Meta", "name": "Meta", "type_vars": []}, "flags": [], "fullname": "quiz.serializers.SkillTypeSerializer.Meta", "metaclass_type": null, "metadata": {}, "module_name": "quiz.serializers", "mro": ["quiz.serializers.SkillTypeSerializer.Meta", "builtins.object"], "names": {".class": "SymbolTable", "fields": {".class": "SymbolTableNode", "kind": "Mdef", "node": {".class": "Var", "flags": ["is_initialized_in_class"], "fullname": "quiz.serializers.SkillTypeSerializer.Meta.fields", "name": "fields", "type": {".class": "Instance", "args": ["builtins.str"], "type_ref": "builtins.list"}}}, "model": {".class": "SymbolTableNode", "kind": "Mdef", "node": {".class": "Var", "flags": ["is_initialized_in_class"], "fullname": "quiz.serializers.SkillTypeSerializer.Meta.model", "name": "model", "type": {".class": "CallableType", "arg_kinds": [2, 4], "arg_names": ["_args", "_kwds"], "arg_types": [{".class": "AnyType", "missing_import_name": null, "source_any": null, "type_of_any": 6}, {".class": "AnyType", "missing_import_name": null, "source_any": null, "type_of_any": 6}], "bound_args": [], "def_extras": {}, "fallback": "builtins.type", "implicit": false, "is_ellipsis_args": false, "name": null, "ret_type": "quiz.models.SkillType", "variables": []}}}}, "tuple_type": null, "type_vars": [], "typeddict_type": null}}}, "tuple_type": null, "type_vars": [], "typeddict_type": null}}, "__doc__": {".class": "SymbolTableNode", "kind": "Gdef", "node": {".class": "Var", "flags": [], "fullname": "quiz.serializers.__doc__", "name": "__doc__", "type": "builtins.str"}}, "__file__": {".class": "SymbolTableNode", "kind": "Gdef", "node": {".class": "Var", "flags": [], "fullname": "quiz.serializers.__file__", "name": "__file__", "type": "builtins.str"}}, "__name__": {".class": "SymbolTableNode", "kind": "Gdef", "node": {".class": "Var", "flags": [], "fullname": "quiz.serializers.__name__", "name": "__name__", "type": "builtins.str"}}, "__package__": {".class": "SymbolTableNode", "kind": "Gdef", "node": {".class": "Var", "flags": [], "fullname": "quiz.serializers.__package__", "name": "__package__", "type": "builtins.str"}}, "serializers": {".class": "SymbolTableNode", "kind": "Gdef", "node": {".class": "Var", "flags": ["is_suppressed_import"], "fullname": "quiz.serializers.serializers", "name": "serializers", "type": {".class": "AnyType", "missing_import_name": "quiz.serializers.serializers", "source_any": null, "type_of_any": 3}}}}, "path": "e:\\My Projects\\Backend\\Django\\E-learning\\quiz\\serializers.py"}